TRAMAS/__init__.py
TRAMAS/creartramas.py
robotframework_creartramas-2.2.1.dist-info/LICENSE
robotframework_creartramas-2.2.1.dist-info/METADATA
robotframework_creartramas-2.2.1.dist-info/WHEEL
robotframework_creartramas-2.2.1.dist-info/RECORD
