Metadata-Version: 2.1
Name: robotframework-creartramas
Version: 2.2.1
Summary: Creacion de tramas en hexadecimal
Home-page: https://pypi.org/project/robotframework-creartramas
License: Apache-2.0
Author: Anthony Arevalo
Maintainer: Anthony Arevalo
Requires-Python: >=3.8,<4.0
Classifier: License :: OSI Approved :: Apache Software License
Classifier: Programming Language :: Python :: 3
Classifier: Programming Language :: Python :: 3.8
Classifier: Programming Language :: Python :: 3.9
Classifier: Programming Language :: Python :: 3.10
Classifier: Programming Language :: Python :: 3.11
Classifier: Programming Language :: Python :: 3.12
Requires-Dist: opencv-python (>=4.5.5,<5.0.0)
Requires-Dist: robotframework (>=4)
Requires-Dist: robotframework-pythonlibcore (>=3)
